LICENSE
MANIFEST.in
README.rst
setup.py
salt_verifier.egg-info/PKG-INFO
salt_verifier.egg-info/SOURCES.txt
salt_verifier.egg-info/dependency_links.txt
salt_verifier.egg-info/entry_points.txt
salt_verifier.egg-info/not-zip-safe
salt_verifier.egg-info/requires.txt
salt_verifier.egg-info/top_level.txt
saltverifier/__init__.py
saltverifier/client.py
saltverifier/server.py
saltverifier/upstart.py