Metadata-Version: 1.1
Name: salt-verifier
Version: 0.1.2
Summary: salt-verifier - The salt verifier
Home-page: https://github.com/virtru-ops/salt-verifier
Author: Reuven V. Gonzales
Author-email: reuven@virtru.com
License: MIT
Platform: *nix
Classifier: License :: OSI Approved :: MIT License
Classifier: Intended Audience :: Developers
Classifier: Programming Language :: Python
Classifier: Operating System :: POSIX
Classifier: Topic :: Software Development :: Build Tools
